{
  "id": "et",
  "name": "Quiz - SIET",
  "list": [
    {
      "question": "หากจะเข้าสาขาเทคโนโลยีการศึกษาแพทย์ศาสตร์ต้องเรียนจบม.ปลายสายอะไร",
      "type": "choice",
      "choices": [
        "วิทย์-คณิต",
        "ศิลป์-ภาษา",
        "ศิลป์-คำนวณ",
        "ได้ทุกสาย"
      ]
    },
    {
      "question": "หากจะสอบเข้ารอบที่ 3 (รับตรง) มีเกณฑ์เฉพาะอย่างไร",
      "type": "choice",
      "choices": [
        "เกรดเฉลี่ยมากกว่า 3.50",
        "ได้เกรด 4 วิชาศิลปะทุกเทอม",
        "มีการสอบวิชาวาดเส้น (วิชาเฉพาะ)",
        "ได้คะแนน gat 6 เต็ม"
      ]
    },
    {
      "question": "เอกลักษณ์ของสาขานี้คืออะไร",
      "type": "choice",
      "choices": [
        "รักษาคนไข้",
        "ผลิตสื่อทางการแพทย์",
        "ทำอวัยวะเทียม",
        "ปรุงยาสมุนไพร"
      ]
    },
    {
      "question": "วิชาใดที่ไม่มีในหลักสูตรเทคโนโลยีการศึกษาแพทย์",
      "type": "choice",
      "choices": [
        "แคลคูลัส",
        "ถ่ายภาพ",
        "กายวิภาคศาสตร์",
        "การวาดภาพหุ่นนิ่ง"
      ]
    },
    {
      "question": "สาขานี้เรียนกี่ปี",
      "type": "choice",
      "choices": [
        "1 ปี",
        "4 ปี",
        "6 ปี",
        "8 ปี"
      ]
    },
    {
      "question": "สาขาเทคโนโลยีการศึกษาแพทย์ศาสตร์ จบมาได้วุฒิอะไร",
      "type": "choice",
      "choices": [
        "แพทยศาสตร์บัณฑิต",
        "วิทยาศาสตร์บัณฑิต",
        "เทคโนโลยีบัณฑิต",
        "ถูกทุกข้อ"
      ]
    },
    {
      "question": "เมื่อเรียนจบสามารถทำอาชีพอะไรได้บ้าง",
      "type": "choice",
      "choices": [
        "นักเวชนิทัศน์",
        "ฟรีแลนซ์",
        "กราฟฟิคดีไซน์",
        "ถูกทุกข้อ"
      ]
    },
    {
      "question": "สาขาเทคโนโลยีการศึกษาแพทย์ศาสตร์ จบแล้วสามารถเป็นแพทย์รักษาคนไข้ได้หรือไม่",
      "type": "choice",
      "choices": [
        "ได้",
        "ไม่ได้",
        "ต้องเรียนต่ออีก 2 ปี",
        "เป็นผู้ช่วยได้"
      ]
    },
    {
      "question": "ค่ายของสาขามีชื่อว่าอะไร",
      "type": "choice",
      "choices": [
        "ค่ายเด็กวิทย์หัวใจศิลป์",
        "ค่ายเส้นทางสู่แพทย์ศิริราช",
        "ค่ายเเต้มสีสู่ฝัน",
        "ค่ายปลายพู่กัน"
      ]
    },
    {
      "question": "MET exhibition คืออะไร",
      "type": "choice",
      "choices": [
        "ค่ายของสาขา",
        "ชื่องานโอเพ้นเฮ้าส์ของสาขา",
        "นิทรรศการแสดงผลงานของนักศึกษาในสาขา",
        "กิจกรรมรับน้องที่จัดขึ้นให้เเก่นักศึกษาปี 2 เป็นประจำทุกปี"
      ]
    }
  ]
}